bolero/__init__.py
bolero/utils.py
bolero/pkg_data/cbust
bolero/pkg_data/cbust_macos
bolero/pkg_data/blacklist_v2/hg19-blacklist.v2.bed.gz
bolero/pkg_data/blacklist_v2/hg38-blacklist.v2.bed.gz
bolero/pkg_data/blacklist_v2/mm10-blacklist.v2.bed.gz
bolero/pkg_data/encode_screen_cCREs/GRCh38-cCREs.bed.gz
bolero/pkg_data/encode_screen_cCREs/mm10-cCREs.bed.gz
bolero/pkg_data/jaspar/JASPAR2024_CORE_diatoms_non-redundant_pfms_jaspar.motif_pwm.dict
bolero/pkg_data/jaspar/JASPAR2024_CORE_fungi_non-redundant_pfms_jaspar.motif_pwm.dict
bolero/pkg_data/jaspar/JASPAR2024_CORE_insects_non-redundant_pfms_jaspar.motif_pwm.dict
bolero/pkg_data/jaspar/JASPAR2024_CORE_nematodes_non-redundant_pfms_jaspar.motif_pwm.dict
bolero/pkg_data/jaspar/JASPAR2024_CORE_non-redundant_pfms_jaspar.motif_pwm.dict
bolero/pkg_data/jaspar/JASPAR2024_CORE_plants_non-redundant_pfms_jaspar.motif_pwm.dict
bolero/pkg_data/jaspar/JASPAR2024_CORE_urochordates_non-redundant_pfms_jaspar.motif_pwm.dict
bolero/pkg_data/jaspar/JASPAR2024_CORE_vertebrates_non-redundant_pfms_jaspar.motif_pwm.dict
bolero/pl/__init__.py
bolero/pl/footprint.py
bolero/pl/motif_track.py
bolero/pl/seqlogo.py
bolero/pl/track1d.py
bolero/pl/utils.py
bolero/pp/__init__.py
bolero/pp/genome.py
bolero/pp/genome_chunk_dataset.py
bolero/pp/genome_dataset.py
bolero/pp/normalize.py
bolero/pp/prepare_ray_dataset.py
bolero/pp/ray_chunk_dataset.py
bolero/pp/seq.py
bolero/pp/utils.py
bolero/tl/__init__.py
bolero/tl/dataset/__init__.py
bolero/tl/dataset/file_transforms.py
bolero/tl/dataset/filters.py
bolero/tl/dataset/ray_dataset.py
bolero/tl/dataset/sc_transforms.py
bolero/tl/dataset/transforms.py
bolero/tl/dataset/archive/dataset.py
bolero/tl/footprint/__init__.py
bolero/tl/footprint/footprint.py
bolero/tl/footprint/segment.py
bolero/tl/footprint/tfbs.py
bolero/tl/footprint/utils.py
bolero/tl/generic/__init__.py
bolero/tl/generic/dataset.py
bolero/tl/generic/ema.py
bolero/tl/generic/module.py
bolero/tl/generic/train.py
bolero/tl/generic/train_helper.py
bolero-0.0.35.dist-info/METADATA
bolero-0.0.35.dist-info/WHEEL
bolero-0.0.35.dist-info/entry_points.txt
bolero-0.0.35.dist-info/licenses/LICENSE
bolero-0.0.35.dist-info/RECORD
