Metadata-Version: 2.3
Name: bolero
Version: 0.0.35
Summary: sequence
Project-URL: Documentation, https://bolero.readthedocs.io/
Project-URL: Source, https://github.com/lhqing/bolero
Project-URL: Home-page, https://github.com/lhqing/bolero
Author: Hanqing Liu, Hanchen Wang
Maintainer-email: Hanqing Liu <hanqingliu@fas.harvard.edu>, Hanchen Wang <hanchenw.au@gmail.com>
License: MIT License
License-File: LICENSE
Requires-Python: >=3.6
Requires-Dist: anndata
Requires-Dist: beartype
Requires-Dist: biopython
Requires-Dist: bolero-process
Requires-Dist: click
Requires-Dist: deeptools
Requires-Dist: gensim
Requires-Dist: geosketch
Requires-Dist: joblib
Requires-Dist: pyfaidx
Requires-Dist: pynndescent
Requires-Dist: pyranges
Requires-Dist: seaborn
Requires-Dist: session-info
Requires-Dist: tmtoolkit
Requires-Dist: tqdm
Requires-Dist: transformers
Requires-Dist: wandb
Requires-Dist: xarray
Requires-Dist: zarr
Provides-Extra: dev
Requires-Dist: pre-commit; extra == 'dev'
Requires-Dist: twine>=4.0.2; extra == 'dev'
Provides-Extra: doc
Requires-Dist: docutils!=0.18.*,!=0.19.*,>=0.8; extra == 'doc'
Requires-Dist: ipykernel; extra == 'doc'
Requires-Dist: ipython; extra == 'doc'
Requires-Dist: jupyterlab; extra == 'doc'
Requires-Dist: myst-nb; extra == 'doc'
Requires-Dist: pandas; extra == 'doc'
Requires-Dist: sphinx-autodoc-typehints; extra == 'doc'
Requires-Dist: sphinx-book-theme>=1.0.0; extra == 'doc'
Requires-Dist: sphinx-copybutton; extra == 'doc'
Requires-Dist: sphinx>=4; extra == 'doc'
Requires-Dist: sphinxcontrib-bibtex>=1.0.0; extra == 'doc'
Requires-Dist: sphinxext-opengraph; extra == 'doc'
Provides-Extra: test
Requires-Dist: coverage; extra == 'test'
Requires-Dist: pytest; extra == 'test'
